AUTHORS
LICENSE
MANIFEST.in
README.rst
TODO.md
setup.py
docs/.DS_Store
docs/.gitignore
docs/Makefile
docs/conf.py
docs/index.rst
docs/make.bat
fits_viewer.egg-info/PKG-INFO
fits_viewer.egg-info/SOURCES.txt
fits_viewer.egg-info/dependency_links.txt
fits_viewer.egg-info/entry_points.txt
fits_viewer.egg-info/requires.txt
fits_viewer.egg-info/top_level.txt
fitsviewer/__init__.py
fitsviewer/gui/__init__.py
fitsviewer/gui/tk_matplotlib.py
fitsviewer/utils/__init__.py
fitsviewer/utils/fits2png.py
fitsviewer/utils/png2fits.py